openai_api/prompt.py
openai_api/wrapper.py
KergaAI-1.1.1.dist-info/METADATA
KergaAI-1.1.1.dist-info/WHEEL
KergaAI-1.1.1.dist-info/top_level.txt
KergaAI-1.1.1.dist-info/RECORD
