Metadata-Version: 2.1
Name: KergaAI
Version: 1.1.1
Summary: A wrapper to the OpenAI API
Author: GD
Classifier: Intended Audience :: Developers
Classifier: License :: OSI Approved :: MIT License
Classifier: Programming Language :: Python :: 3.11
Requires-Dist: wheel
Requires-Dist: twine
Requires-Dist: openai (==0.27.8)
Requires-Dist: python-dotenv (==1.0.0)
